lavague/core/__init__.py
lavague/core/action_engine.py
lavague/core/action_template.py
lavague/core/agents.py
lavague/core/base_driver.py
lavague/core/base_engine.py
lavague/core/context.py
lavague/core/display.py
lavague/core/evaluator.py
lavague/core/exceptions.py
lavague/core/extractors.py
lavague/core/logger.py
lavague/core/memory.py
lavague/core/navigation.py
lavague/core/python_engine.py
lavague/core/retrievers.py
lavague/core/token_counter.py
lavague/core/utilities/config.py
lavague/core/utilities/format_utils.py
lavague/core/utilities/model_utils.py
lavague/core/utilities/pricing_config.yml
lavague/core/utilities/pricing_util.py
lavague/core/utilities/telemetry.py
lavague/core/utilities/unicode_animation.py
lavague/core/utilities/version_checker.py
lavague/core/utilities/web_utils.py
lavague/core/world_model.py
lavague_core-0.2.34.dist-info/LICENSE
lavague_core-0.2.34.dist-info/METADATA
lavague_core-0.2.34.dist-info/WHEEL
lavague_core-0.2.34.dist-info/RECORD
