Metadata-Version: 2.1
Name: lavague-core
Version: 0.2.34
Summary: automation code generation from text instructions
Home-page: https://lavague.ai
License: Apache-2.0
Keywords: LAM,action,automation,LLM,NLP,RAG,selenium,playwright
Author: lavague-ai
Requires-Python: >=3.10.0,<4.0.0
Classifier: Development Status :: 3 - Alpha
Classifier: Intended Audience :: Developers
Classifier: License :: OSI Approved :: Apache Software License
Classifier: Programming Language :: Python :: 3
Classifier: Programming Language :: Python :: 3.10
Classifier: Programming Language :: Python :: 3.11
Classifier: Programming Language :: Python :: 3.12
Classifier: Topic :: Scientific/Engineering :: Artificial Intelligence
Classifier: Topic :: Software Development :: Libraries :: Application Frameworks
Classifier: Topic :: Software Development :: Libraries :: Python Modules
Requires-Dist: PyYAML (>=5.3)
Requires-Dist: ipython (>=7.34.0,<8.0.0)
Requires-Dist: jsonschema (>=4.23.0,<5.0.0)
Requires-Dist: langchain (>=0.1.20,<0.2.0)
Requires-Dist: llama-index (==0.10.56)
Requires-Dist: llama-index-retrievers-bm25 (>=0.1.3,<0.2.0)
Requires-Dist: lxml (>=5.1.1,<6.0.0)
Requires-Dist: lxml-html-clean (>=0.1.1,<0.2.0)
Requires-Dist: msgpack (>=1.0.8,<2.0.0)
Requires-Dist: seaborn (>=0.13.2,<0.14.0)
Requires-Dist: tenacity (>=8.2.0,<8.4.0)
Requires-Dist: trafilatura (>=1.9.0,<2.0.0)
Project-URL: Documentation, https://docs.lavague.ai/en/latest/
Project-URL: Repository, https://github.com/lavague-ai/LaVague/
